r53_provider/manifest.toml
r53_provider/r53_provider.py
r53_provider/test_r53_provider.py
opsbox_r53_provider-0.1.5.dist-info/LICENCE.txt
opsbox_r53_provider-0.1.5.dist-info/METADATA
opsbox_r53_provider-0.1.5.dist-info/WHEEL
opsbox_r53_provider-0.1.5.dist-info/entry_points.txt
opsbox_r53_provider-0.1.5.dist-info/top_level.txt
opsbox_r53_provider-0.1.5.dist-info/RECORD
