Metadata-Version: 2.2
Name: opsbox-r53-provider
Version: 0.1.5
Summary: Opsbox provider for Route 53 checks
Requires-Python: ==3.11.*
License-File: LICENCE.txt
Requires-Dist: boto3>=1.35.71
Requires-Dist: loguru>=0.7.2
Requires-Dist: pluggy>=1.5.0
Requires-Dist: opsbox-general-handler>=0.1.2
